{
  "formulae": [],
  "casks": [
    {
      "token": "fafarunner",
      "full_token": "fafarunner",
      "old_tokens": [],
      "tap": null,
      "name": [
        "FaFa Runner"
      ],
      "desc": "Enjoy smooth gameplay, stunning graphics, and endless fun",
      "homepage": "https://fafarunner.com/",
      "url": "https://github.com/fafarunner/fafarunner/releases/download/v1.0.7+373/FaFaRunner_1.0.7+373_macos_universal.dmg",
      "url_specs": {
        "verified": "github.com/fafarunner/fafarunner/"
      },
      "version": "1.0.7+373",
      "installed": null,
      "installed_time": null,
      "bundle_version": null,
      "bundle_short_version": null,
      "outdated": false,
      "sha256": "c5dac821c80a89114dcca483307b1efcfdb2d24c90e5e3e7bddebca4c4dda3b3",
      "artifacts": [
        {
          "app": [
            "FaFa Runner.app"
          ]
        },
        {
          "zap": [
            {
              "trash": [
                "~/Library/Application Support/FaFa Runner",
                "~/Library/Caches/com.chenyifaer.fafarunner",
                "~/Library/Caches/FaFa Runner",
                "~/Library/Preferences/com.chenyifaer.fafarunner.plist",
                "~/Library/Saved Application State/com.chenyifaer.fafarunner.savedState"
              ]
            }
          ]
        }
      ],
      "caveats": null,
      "depends_on": {
        "macos": {
          ">=": [
            "10.15"
          ]
        }
      },
      "conflicts_with": null,
      "container": null,
      "auto_updates": null,
      "deprecated": false,
      "deprecation_date": null,
      "deprecation_reason": null,
      "deprecation_replacement": null,
      "disabled": false,
      "disable_date": null,
      "disable_reason": null,
      "disable_replacement": null,
      "tap_git_head": null,
      "languages": [],
      "ruby_source_path": null,
      "ruby_source_checksum": {
        "sha256": "de44a0ce6cfc8b3c173857d1c26a9106d12b464926131534e0272e23b8a338b1"
      }
    }
  ]
}
